nonebot_plugin_arkgacha-0.8.2.dist-info/METADATA
nonebot_plugin_arkgacha-0.8.2.dist-info/WHEEL
nonebot_plugin_arkgacha-0.8.2.dist-info/entry_points.txt
nonebot_plugin_arkgacha-0.8.2.dist-info/licenses/LICENSE
nonebot_plugin_arkgacha/__init__.py
nonebot_plugin_arkgacha/__main__.py
nonebot_plugin_arkgacha/config.py
nonebot_plugin_arkgacha-0.8.2.dist-info/RECORD
