Metadata-Version: 2.1
Name: nonebot-plugin-arkgacha
Version: 0.8.2
Summary: Plugin for Arknights gacha, support multi platform
Author-Email: RF-Tar-Railt <rf_tar_railt@qq.com>
License: MIT
Requires-Python: >=3.9
Requires-Dist: nonebot2>=2.3.0
Requires-Dist: nonebot-plugin-alconna>=0.54.0
Requires-Dist: arknights-toolkit>=0.7.7
Requires-Dist: nonebot-plugin-localstore>=0.6.0
Requires-Dist: nonebot-plugin-apscheduler>=0.4.0
